pg_elastic/__init__.py
pg_elastic/replicate_es.py
pg_replicate_elastic-1.0.3.data/scripts/pg_replicate_elastic
pg_replicate_elastic-1.0.3.dist-info/METADATA
pg_replicate_elastic-1.0.3.dist-info/RECORD
pg_replicate_elastic-1.0.3.dist-info/WHEEL
pg_replicate_elastic-1.0.3.dist-info/top_level.txt
