Metadata-Version: 2.1
Name: pg-replicate-elastic
Version: 1.0.3
Summary: Replication PostreSQL to Elasticsearch via Logical replication slots
Home-page: https://git.krakensystems.co/KrakenSystems/pg-replicate-elastic
Author: Hrvoje Milkovic
Author-email: hrvoje@krakensystems.co
License: MIT
Keywords: postgresql,elasticsearch,replication
Platform: UNKNOWN
Requires-Dist: docopt (==0.6.2)
Requires-Dist: elasticsearch (==6.1.1)
Requires-Dist: et-xmlfile (==1.0.1)
Requires-Dist: jdcal (==1.3)
Requires-Dist: odfpy (==1.3.6)
Requires-Dist: openpyxl (==2.5.0)
Requires-Dist: psycopg2 (==2.7.4)
Requires-Dist: psycopg2-binary (==2.7.4)
Requires-Dist: python-dateutil (==2.6.1)
Requires-Dist: PyYAML (==3.12)
Requires-Dist: records (==0.5.2)
Requires-Dist: six (==1.11.0)
Requires-Dist: SQLAlchemy (==1.2.2)
Requires-Dist: tablib (==0.12.1)
Requires-Dist: unicodecsv (==0.14.1)
Requires-Dist: urllib3 (==1.22)
Requires-Dist: xlrd (==1.1.0)
Requires-Dist: xlwt (==1.3.0)
